django_rediscache
