Metadata-Version: 1.0
Name: django-rediscache
Version: 1.0.5
Summary: Django ORM cached tools in Redis.
Home-page: UNKNOWN
Author: Michael Vorotyntsev
Author-email: linkofwise@gmail.com
License: UNKNOWN
Platform: UNKNOWN
